LICENSE
README.md
setup.py
aqur1n_tools.egg-info/PKG-INFO
aqur1n_tools.egg-info/SOURCES.txt
aqur1n_tools.egg-info/dependency_links.txt
aqur1n_tools.egg-info/not-zip-safe
aqur1n_tools.egg-info/top_level.txt
atools/None.py
atools/__init__.py
atools/basic.py
atools/cache.py
atools/cfg.py
atools/path.py
atools/sqlite3.py