Metadata-Version: 2.1
Name: aqur1n-tools
Version: 2022.2.12
Summary: Collection of modules for convenient work.
Home-page: https://github.com/aqur1n-lab/aqur1n-tools
Author: aqur1n
License: MIT
Project-URL: Bug Tracker, https://github.com/aqur1n-lab/aqur1n-tools/issues
Project-URL: Wiki, https://github.com/aqur1n-lab/aqur1n-tools/wiki
Platform: UNKNOWN
Classifier: Programming Language :: Python :: 3
Classifier: License :: OSI Approved :: MIT License
Classifier: Operating System :: OS Independent
Requires-Python: >=3.8
License-File: LICENSE
